webis/SentimentIdentifier.py
webis/__init__.py
webis/__main__.py
webis/_version.py
webis/util.py
webis-0.3.1.dist-info/LICENSE
webis-0.3.1.dist-info/METADATA
webis-0.3.1.dist-info/WHEEL
webis-0.3.1.dist-info/top_level.txt
webis-0.3.1.dist-info/RECORD
