Metadata-Version: 2.1
Name: webis
Version: 0.3.1
Summary: Python wrapper for the webis Twitter sentiment identification tool
Home-page: https://gitlab.com/christoph.fink/python-webis
Author: Christoph Fink
Author-email: christoph.fink@helsinki.fi
License: GPLv3
Platform: UNKNOWN
Classifier: Programming Language :: Python :: 3
Classifier: License :: OSI Approved :: GNU General Public License v3 (GPLv3)
Classifier: Operating System :: OS Independent
Requires-Dist: emojientities
Requires-Dist: GitPython
Requires-Dist: jnius
Requires-Dist: pandas
Requires-Dist: versioneer
